django_rest_commons/__init__.py
django_rest_commons/mixins.py
django_rest_commons/serializers.py
django_rest_commons/utils.py
django_rest_commons/viewsets.py
django_rest_commons-1.0.6.dist-info/LICENSE.txt
django_rest_commons-1.0.6.dist-info/METADATA
django_rest_commons-1.0.6.dist-info/WHEEL
django_rest_commons-1.0.6.dist-info/top_level.txt
django_rest_commons-1.0.6.dist-info/RECORD
