Metadata-Version: 2.1
Name: django-rest-commons
Version: 1.0.6
Summary: Django rest framework common utilities
Home-page: https://github.com/LeOndaz/drf-rest-commons
Author: LeOndaz
Author-email: ahmeddark369@gmail.com
License-File: LICENSE.txt
